iowarp_mcps/__init__.py
iowarp_mcps-0.3.11.data/data/mcps/Adios/.gitignore
iowarp_mcps-0.3.11.data/data/mcps/Adios/README.md
iowarp_mcps-0.3.11.data/data/mcps/Adios/pyproject.toml
iowarp_mcps-0.3.11.data/data/mcps/Adios/uv.lock
iowarp_mcps-0.3.11.data/data/mcps/Adios/data/data1.bp/data.0
iowarp_mcps-0.3.11.data/data/mcps/Adios/data/data1.bp/md.0
iowarp_mcps-0.3.11.data/data/mcps/Adios/data/data1.bp/md.idx
iowarp_mcps-0.3.11.data/data/mcps/Adios/data/data1.bp/mmd.0
iowarp_mcps-0.3.11.data/data/mcps/Adios/data/data2.bp/data.0
iowarp_mcps-0.3.11.data/data/mcps/Adios/data/data2.bp/md.0
iowarp_mcps-0.3.11.data/data/mcps/Adios/data/data2.bp/md.idx
iowarp_mcps-0.3.11.data/data/mcps/Adios/data/data2.bp/mmd.0
iowarp_mcps-0.3.11.data/data/mcps/Adios/data/data3.bp/data.0
iowarp_mcps-0.3.11.data/data/mcps/Adios/data/data3.bp/md.0
iowarp_mcps-0.3.11.data/data/mcps/Adios/data/data3.bp/md.idx
iowarp_mcps-0.3.11.data/data/mcps/Adios/data/data3.bp/mmd.0
iowarp_mcps-0.3.11.data/data/mcps/Adios/data/data4.bp/data.0
iowarp_mcps-0.3.11.data/data/mcps/Adios/data/data4.bp/md.0
iowarp_mcps-0.3.11.data/data/mcps/Adios/data/data4.bp/md.idx
iowarp_mcps-0.3.11.data/data/mcps/Adios/data/data4.bp/mmd.0
iowarp_mcps-0.3.11.data/data/mcps/Adios/docs/adios_setup.md
iowarp_mcps-0.3.11.data/data/mcps/Adios/docs/basic_install.md
iowarp_mcps-0.3.11.data/data/mcps/Adios/docs/example_uses.md
iowarp_mcps-0.3.11.data/data/mcps/Adios/src/mcp_handlers.py
iowarp_mcps-0.3.11.data/data/mcps/Adios/src/server.py
iowarp_mcps-0.3.11.data/data/mcps/Adios/src/implementation/__init__.py
iowarp_mcps-0.3.11.data/data/mcps/Adios/src/implementation/bp5_attributes.py
iowarp_mcps-0.3.11.data/data/mcps/Adios/src/implementation/bp5_inspect_variables.py
iowarp_mcps-0.3.11.data/data/mcps/Adios/src/implementation/bp5_inspect_variables_at_step.py
iowarp_mcps-0.3.11.data/data/mcps/Adios/src/implementation/bp5_list.py
iowarp_mcps-0.3.11.data/data/mcps/Adios/src/implementation/bp5_read_variable_at_step.py
iowarp_mcps-0.3.11.dist-info/METADATA
iowarp_mcps-0.3.11.dist-info/WHEEL
iowarp_mcps-0.3.11.dist-info/entry_points.txt
iowarp_mcps-0.3.11.dist-info/RECORD
