Metadata-Version: 2.4
Name: iowarp-mcps
Version: 0.3.11
Summary: Open Source MCP Servers for Scientific Computing
Project-URL: Homepage, https://github.com/iowarp/iowarp-mcps
Project-URL: Repository, https://github.com/iowarp/iowarp-mcps
Project-URL: Issues, https://github.com/iowarp/iowarp-mcps/issues
Author-email: IOWarp Team <team@iowarp.com>
License: MIT
Requires-Python: >=3.10
Requires-Dist: click>=8.1.0
